conda_sphinx_theme/__init__.py
conda_sphinx_theme/_version.py
conda_sphinx_theme/layout.html
conda_sphinx_theme/theme.conf
conda_sphinx_theme/version_anchors.py
conda_sphinx_theme/_templates/conda_icon_links.html
conda_sphinx_theme/_templates/footer_center.html
conda_sphinx_theme/_templates/navbar_center.html
conda_sphinx_theme/_templates/sidebar-nav-bs.html
conda_sphinx_theme/static/conda_logo.svg
conda_sphinx_theme/static/conda_logo_full.svg
conda_sphinx_theme/static/favicon.ico
conda_sphinx_theme/static/zulip_logo.svg
conda_sphinx_theme/static/css/style.css
conda_sphinx_theme/static/fonts/nunito-bold-webfont.woff
conda_sphinx_theme/static/fonts/nunito-bold-webfont.woff2
conda_sphinx_theme/static/fonts/nunito-bolditalic-webfont.woff
conda_sphinx_theme/static/fonts/nunito-bolditalic-webfont.woff2
conda_sphinx_theme/static/fonts/nunito-italic-webfont.woff
conda_sphinx_theme/static/fonts/nunito-italic-webfont.woff2
conda_sphinx_theme/static/fonts/nunito-regular-webfont.woff
conda_sphinx_theme/static/fonts/nunito-regular-webfont.woff2
conda_sphinx_theme/static/fonts/opensans-bold-webfont.woff
conda_sphinx_theme/static/fonts/opensans-bold-webfont.woff2
conda_sphinx_theme/static/fonts/opensans-bolditalic-webfont.woff
conda_sphinx_theme/static/fonts/opensans-bolditalic-webfont.woff2
conda_sphinx_theme/static/fonts/opensans-italic-webfont.woff
conda_sphinx_theme/static/fonts/opensans-italic-webfont.woff2
conda_sphinx_theme/static/fonts/opensans-regular-webfont.woff
conda_sphinx_theme/static/fonts/opensans-regular-webfont.woff2
conda_sphinx_theme/static/js/count.js
conda_sphinx_theme-0.3.0.dist-info/licenses/LICENSE
conda_sphinx_theme-0.3.0.dist-info/METADATA
conda_sphinx_theme-0.3.0.dist-info/WHEEL
conda_sphinx_theme-0.3.0.dist-info/entry_points.txt
conda_sphinx_theme-0.3.0.dist-info/top_level.txt
conda_sphinx_theme-0.3.0.dist-info/RECORD
