Metadata-Version: 2.4
Name: conda_sphinx_theme
Version: 0.3.0
Summary: Conda theme for Sphinx
Author: Travs Hathaway
License: BSD 3-Clause License
Project-URL: homepage, https://github.com/conda-incubator/conda-sphinx-theme/
Project-URL: repository, https://github.com/conda-incubator/conda-sphinx-theme
Classifier: Framework :: Sphinx :: Theme
Classifier: Programming Language :: Python :: 3 :: Only
Classifier: Topic :: Documentation
Classifier: Topic :: Documentation :: Sphinx
Requires-Python: >=3
License-File: LICENSE
Requires-Dist: pydata-sphinx-theme<0.16.0,>=0.13.1
Requires-Dist: sphinx-favicon
Dynamic: license-file
